<annotation>
	<folder>ship</folder>
	<filename>s0098.png</filename>
	<path>C:\Users\Tofahito\Documents\PHD\barcos\etiquetas\ship\s0098.png</path>
	<source>
		<database>Unknown</database>
	</source>
	<size>
		<width>512</width>
		<height>512</height>
		<depth>3</depth>
	</size>
	<segmented>0</segmented>
	<object>
		<name>ship</name>
		<pose>Unspecified</pose>
		<truncated>0</truncated>
		<difficult>0</difficult>
		<bndbox>
			<xmin>209</xmin>
			<ymin>223</ymin>
			<xmax>225</xmax>
			<ymax>240</ymax>
		</bndbox>
	</object>
</annotation>
